iyake_cn/__init__.py
iyake_cn/iyake_cn.py
iyake_cn-0.5.5.dist-info/LICENSE
iyake_cn-0.5.5.dist-info/METADATA
iyake_cn-0.5.5.dist-info/WHEEL
iyake_cn-0.5.5.dist-info/top_level.txt
iyake_cn-0.5.5.dist-info/RECORD
