Metadata-Version: 2.1
Name: iyake-cn
Version: 0.5.5
Summary: get key words from chinese content
Home-page: https://blog.csdn.net/zohan134
Author: Seon
Author-email: 781091978@qq.com
License-File: LICENSE
